msfinance/__init__.py
msfinance/stocks.py
msfinance-0.4.0.dist-info/LICENSE
msfinance-0.4.0.dist-info/METADATA
msfinance-0.4.0.dist-info/WHEEL
msfinance-0.4.0.dist-info/top_level.txt
msfinance-0.4.0.dist-info/RECORD
