Metadata-Version: 2.2
Name: msfinance
Version: 0.4.0
Summary: msfinance offers Pythonic way to download stocks financial data from morningstar.com
Author-email: Jimmy Situ <web@jimmystone.com>
License:                                  Apache License
Project-URL: Homepage, https://github.com/jimmysitu/msfinance
Project-URL: Bug Tracker, https://github.com/jimmysitu/msfinance/issues
Classifier: Programming Language :: Python :: 3
Classifier: License :: OSI Approved :: Apache Software License
Classifier: Operating System :: OS Independent
Requires-Python: >=3.8
License-File: LICENSE
Requires-Dist: xlrd
Requires-Dist: lxml
Requires-Dist: requests
Requires-Dist: pandas
Requires-Dist: tenacity
Requires-Dist: selenium
Requires-Dist: sqlalchemy
Requires-Dist: fake-useragent<2.0.0
Requires-Dist: selenium-stealth
Requires-Dist: undetected-chromedriver
Requires-Dist: webdriver-manager
